setup.py
py_search_game_algos.egg-info/PKG-INFO
py_search_game_algos.egg-info/SOURCES.txt
py_search_game_algos.egg-info/dependency_links.txt
py_search_game_algos.egg-info/requires.txt
py_search_game_algos.egg-info/top_level.txt
py_search_game_algos/searches/__init__.py
py_search_game_algos/searches/advertisal.py
py_search_game_algos/searches/informed.py
py_search_game_algos/searches/local.py
py_search_game_algos/searches/uninformed.py
py_search_game_algos/utile/__init__.py
py_search_game_algos/utile/problem.py
py_search_game_algos/utile/util.py