Metadata-Version: 2.1
Name: py-search-game-algos
Version: 1.0
Summary: py_search_game_algos
License: UNKNOWN
Platform: UNKNOWN
